agent_diff/__init__.py
agent_diff/client.py
agent_diff/code_executor.py
agent_diff/models.py
agent_diff-1.0.6.dist-info/licenses/LICENSE
agent_diff-1.0.6.dist-info/METADATA
agent_diff-1.0.6.dist-info/WHEEL
agent_diff-1.0.6.dist-info/top_level.txt
agent_diff-1.0.6.dist-info/RECORD
