Metadata-Version: 2.4
Name: agent-diff
Version: 1.0.6
Summary: Python SDK for Agent Diff - test AI agents and train models against replicas of services
Author-email: Agent Diff <hubert@uni.minerva.edu>
License: MIT
Project-URL: Repository, https://github.com/hubertpysklo/agent-diff
Project-URL: Documentation, https://github.com/hubertpysklo/agent-diff/tree/main/docs
Classifier: Development Status :: 3 - Alpha
Classifier: Intended Audience :: Developers
Classifier: License :: OSI Approved :: MIT License
Classifier: Programming Language :: Python :: 3
Classifier: Programming Language :: Python :: 3.11
Classifier: Programming Language :: Python :: 3.12
Classifier: Programming Language :: Python :: 3.13
Requires-Python: >=3.11
License-File: LICENSE
Requires-Dist: requests>=2.32.5
Requires-Dist: pydantic>=2.12.1
Requires-Dist: typing-extensions>=4.0.0
Dynamic: license-file
